Metadata-Version: 2.1
Name: apiComs
Version: 1.0.3
Summary: This is a package to stremaline api method calls
Home-page: https://github.com/demecode/winter-api-commons
Author: Deme Xavier
Author-email: clabsvc@gmail.com
License: MIT
Keywords: api automation,api testing,api commons,python api,api automation using pythoncommon repo
Platform: UNKNOWN
Classifier: Development Status :: 5 - Production/Stable
Classifier: Programming Language :: Python :: 3
Classifier: Intended Audience :: Education
License-File: LICENCE.txt
